{"audio_files":[{"id":1485,"chapter_id":1,"file_size":817280.0,"format":"mp3","audio_url":"https://download.quranicaudio.com/quran/muhammad_jibreel/hidayah//001.mp3"},{"id":1487,"chapter_id":36,"file_size":18053248.0,"format":"mp3","audio_url":"https://download.quranicaudio.com/quran/muhammad_jibreel/hidayah//036.mp3"},{"id":1489,"chapter_id":55,"file_size":11069568.0,"format":"mp3","audio_url":"https://download.quranicaudio.com/quran/muhammad_jibreel/hidayah//055.mp3"},{"id":1491,"chapter_id":56,"file_size":10444928.0,"format":"mp3","audio_url":"https://download.quranicaudio.com/quran/muhammad_jibreel/hidayah//056.mp3"},{"id":1493,"chapter_id":73,"file_size":4624512.0,"format":"mp3","audio_url":"https://download.quranicaudio.com/quran/muhammad_jibreel/hidayah//073.mp3"},{"id":1495,"chapter_id":93,"file_size":1063040.0,"format":"mp3","audio_url":"https://download.quranicaudio.com/quran/muhammad_jibreel/hidayah//093.mp3"},{"id":1497,"chapter_id":94,"file_size":706688.0,"format":"mp3","audio_url":"https://download.quranicaudio.com/quran/muhammad_jibreel/hidayah//094.mp3"},{"id":1499,"chapter_id":95,"file_size":1032320.0,"format":"mp3","audio_url":"https://download.quranicaudio.com/quran/muhammad_jibreel/hidayah//095.mp3"},{"id":1501,"chapter_id":96,"file_size":1642624.0,"format":"mp3","audio_url":"https://download.quranicaudio.com/quran/muhammad_jibreel/hidayah//096.mp3"},{"id":1503,"chapter_id":97,"file_size":874624.0,"format":"mp3","audio_url":"https://download.quranicaudio.com/quran/muhammad_jibreel/hidayah//097.mp3"},{"id":1505,"chapter_id":98,"file_size":2259072.0,"format":"mp3","audio_url":"https://download.quranicaudio.com/quran/muhammad_jibreel/hidayah//098.mp3"},{"id":1507,"chapter_id":99,"file_size":944256.0,"format":"mp3","audio_url":"https://download.quranicaudio.com/quran/muhammad_jibreel/hidayah//099.mp3"},{"id":1509,"chapter_id":100,"file_size":1073280.0,"format":"mp3","audio_url":"https://download.quranicaudio.com/quran/muhammad_jibreel/hidayah//100.mp3"},{"id":1511,"chapter_id":101,"file_size":1052800.0,"format":"mp3","audio_url":"https://download.quranicaudio.com/quran/muhammad_jibreel/hidayah//101.mp3"},{"id":1513,"chapter_id":102,"file_size":817280.0,"format":"mp3","audio_url":"https://download.quranicaudio.com/quran/muhammad_jibreel/hidayah//102.mp3"},{"id":1515,"chapter_id":103,"file_size":456832.0,"format":"mp3","audio_url":"https://download.quranicaudio.com/quran/muhammad_jibreel/hidayah//103.mp3"},{"id":1517,"chapter_id":104,"file_size":888960.0,"format":"mp3","audio_url":"https://download.quranicaudio.com/quran/muhammad_jibreel/hidayah//104.mp3"},{"id":1519,"chapter_id":105,"file_size":637056.0,"format":"mp3","audio_url":"https://download.quranicaudio.com/quran/muhammad_jibreel/hidayah//105.mp3"},{"id":1521,"chapter_id":106,"file_size":628864.0,"format":"mp3","audio_url":"https://download.quranicaudio.com/quran/muhammad_jibreel/hidayah//106.mp3"},{"id":1523,"chapter_id":107,"file_size":784512.0,"format":"mp3","audio_url":"https://download.quranicaudio.com/quran/muhammad_jibreel/hidayah//107.mp3"},{"id":1525,"chapter_id":108,"file_size":381056.0,"format":"mp3","audio_url":"https://download.quranicaudio.com/quran/muhammad_jibreel/hidayah//108.mp3"},{"id":1527,"chapter_id":109,"file_size":845952.0,"format":"mp3","audio_url":"https://download.quranicaudio.com/quran/muhammad_jibreel/hidayah//109.mp3"},{"id":1529,"chapter_id":110,"file_size":561280.0,"format":"mp3","audio_url":"https://download.quranicaudio.com/quran/muhammad_jibreel/hidayah//110.mp3"},{"id":1531,"chapter_id":111,"file_size":632960.0,"format":"mp3","audio_url":"https://download.quranicaudio.com/quran/muhammad_jibreel/hidayah//111.mp3"},{"id":1533,"chapter_id":112,"file_size":370816.0,"format":"mp3","audio_url":"https://download.quranicaudio.com/quran/muhammad_jibreel/hidayah//112.mp3"},{"id":1535,"chapter_id":113,"file_size":526464.0,"format":"mp3","audio_url":"https://download.quranicaudio.com/quran/muhammad_jibreel/hidayah//113.mp3"},{"id":1537,"chapter_id":114,"file_size":827520.0,"format":"mp3","audio_url":"https://download.quranicaudio.com/quran/muhammad_jibreel/hidayah//114.mp3"}]}
