{"audio_files":[{"id":14566,"chapter_id":1,"file_size":710784.0,"format":"mp3","audio_url":"https://download.quranicaudio.com/quran/abdullaah_alee_jaabir_studio//001.mp3"},{"id":14567,"chapter_id":2,"file_size":95574144.0,"format":"mp3","audio_url":"https://download.quranicaudio.com/quran/abdullaah_alee_jaabir_studio//002.mp3"},{"id":14568,"chapter_id":3,"file_size":50083968.0,"format":"mp3","audio_url":"https://download.quranicaudio.com/quran/abdullaah_alee_jaabir_studio//003.mp3"},{"id":14569,"chapter_id":4,"file_size":59955328.0,"format":"mp3","audio_url":"https://download.quranicaudio.com/quran/abdullaah_alee_jaabir_studio//004.mp3"},{"id":14570,"chapter_id":5,"file_size":46362752.0,"format":"mp3","audio_url":"https://download.quranicaudio.com/quran/abdullaah_alee_jaabir_studio//005.mp3"},{"id":14571,"chapter_id":6,"file_size":43442304.0,"format":"mp3","audio_url":"https://download.quranicaudio.com/quran/abdullaah_alee_jaabir_studio//006.mp3"},{"id":14572,"chapter_id":7,"file_size":54974592.0,"format":"mp3","audio_url":"https://download.quranicaudio.com/quran/abdullaah_alee_jaabir_studio//007.mp3"},{"id":14573,"chapter_id":8,"file_size":19835008.0,"format":"mp3","audio_url":"https://download.quranicaudio.com/quran/abdullaah_alee_jaabir_studio//008.mp3"},{"id":14574,"chapter_id":9,"file_size":38056064.0,"format":"mp3","audio_url":"https://download.quranicaudio.com/quran/abdullaah_alee_jaabir_studio//009.mp3"},{"id":14575,"chapter_id":10,"file_size":25733248.0,"format":"mp3","audio_url":"https://download.quranicaudio.com/quran/abdullaah_alee_jaabir_studio//010.mp3"},{"id":14576,"chapter_id":11,"file_size":27103360.0,"format":"mp3","audio_url":"https://download.quranicaudio.com/quran/abdullaah_alee_jaabir_studio//011.mp3"},{"id":14577,"chapter_id":12,"file_size":25245824.0,"format":"mp3","audio_url":"https://download.quranicaudio.com/quran/abdullaah_alee_jaabir_studio//012.mp3"},{"id":14578,"chapter_id":13,"file_size":13303936.0,"format":"mp3","audio_url":"https://download.quranicaudio.com/quran/abdullaah_alee_jaabir_studio//013.mp3"},{"id":14579,"chapter_id":14,"file_size":10199168.0,"format":"mp3","audio_url":"https://download.quranicaudio.com/quran/abdullaah_alee_jaabir_studio//014.mp3"},{"id":14580,"chapter_id":15,"file_size":9830528.0,"format":"mp3","audio_url":"https://download.quranicaudio.com/quran/abdullaah_alee_jaabir_studio//015.mp3"},{"id":14581,"chapter_id":16,"file_size":23648384.0,"format":"mp3","audio_url":"https://download.quranicaudio.com/quran/abdullaah_alee_jaabir_studio//016.mp3"},{"id":14582,"chapter_id":17,"file_size":22759552.0,"format":"mp3","audio_url":"https://download.quranicaudio.com/quran/abdullaah_alee_jaabir_studio//017.mp3"},{"id":14583,"chapter_id":18,"file_size":20787328.0,"format":"mp3","audio_url":"https://download.quranicaudio.com/quran/abdullaah_alee_jaabir_studio//018.mp3"},{"id":14584,"chapter_id":19,"file_size":13977728.0,"format":"mp3","audio_url":"https://download.quranicaudio.com/quran/abdullaah_alee_jaabir_studio//019.mp3"},{"id":14585,"chapter_id":20,"file_size":17877120.0,"format":"mp3","audio_url":"https://download.quranicaudio.com/quran/abdullaah_alee_jaabir_studio//020.mp3"},{"id":14586,"chapter_id":21,"file_size":18499712.0,"format":"mp3","audio_url":"https://download.quranicaudio.com/quran/abdullaah_alee_jaabir_studio//021.mp3"},{"id":14587,"chapter_id":22,"file_size":19779712.0,"format":"mp3","audio_url":"https://download.quranicaudio.com/quran/abdullaah_alee_jaabir_studio//022.mp3"},{"id":14588,"chapter_id":23,"file_size":18294912.0,"format":"mp3","audio_url":"https://download.quranicaudio.com/quran/abdullaah_alee_jaabir_studio//023.mp3"},{"id":14589,"chapter_id":24,"file_size":20347008.0,"format":"mp3","audio_url":"https://download.quranicaudio.com/quran/abdullaah_alee_jaabir_studio//024.mp3"},{"id":14590,"chapter_id":25,"file_size":16185472.0,"format":"mp3","audio_url":"https://download.quranicaudio.com/quran/abdullaah_alee_jaabir_studio//025.mp3"},{"id":14591,"chapter_id":26,"file_size":21764224.0,"format":"mp3","audio_url":"https://download.quranicaudio.com/quran/abdullaah_alee_jaabir_studio//026.mp3"},{"id":14592,"chapter_id":27,"file_size":21065856.0,"format":"mp3","audio_url":"https://download.quranicaudio.com/quran/abdullaah_alee_jaabir_studio//027.mp3"},{"id":14593,"chapter_id":28,"file_size":34205824.0,"format":"mp3","audio_url":"https://download.quranicaudio.com/quran/abdullaah_alee_jaabir_studio//028.mp3"},{"id":14594,"chapter_id":29,"file_size":15134848.0,"format":"mp3","audio_url":"https://download.quranicaudio.com/quran/abdullaah_alee_jaabir_studio//029.mp3"},{"id":14595,"chapter_id":30,"file_size":12294272.0,"format":"mp3","audio_url":"https://download.quranicaudio.com/quran/abdullaah_alee_jaabir_studio//030.mp3"},{"id":14596,"chapter_id":31,"file_size":9140352.0,"format":"mp3","audio_url":"https://download.quranicaudio.com/quran/abdullaah_alee_jaabir_studio//031.mp3"},{"id":14597,"chapter_id":32,"file_size":7059584.0,"format":"mp3","audio_url":"https://download.quranicaudio.com/quran/abdullaah_alee_jaabir_studio//032.mp3"},{"id":14598,"chapter_id":33,"file_size":21639296.0,"format":"mp3","audio_url":"https://download.quranicaudio.com/quran/abdullaah_alee_jaabir_studio//033.mp3"},{"id":14599,"chapter_id":34,"file_size":13508736.0,"format":"mp3","audio_url":"https://download.quranicaudio.com/quran/abdullaah_alee_jaabir_studio//034.mp3"},{"id":14600,"chapter_id":35,"file_size":13254784.0,"format":"mp3","audio_url":"https://download.quranicaudio.com/quran/abdullaah_alee_jaabir_studio//035.mp3"},{"id":14601,"chapter_id":36,"file_size":13561984.0,"format":"mp3","audio_url":"https://download.quranicaudio.com/quran/abdullaah_alee_jaabir_studio//036.mp3"},{"id":14602,"chapter_id":37,"file_size":16191616.0,"format":"mp3","audio_url":"https://download.quranicaudio.com/quran/abdullaah_alee_jaabir_studio//037.mp3"},{"id":14603,"chapter_id":38,"file_size":12155008.0,"format":"mp3","audio_url":"https://download.quranicaudio.com/quran/abdullaah_alee_jaabir_studio//038.mp3"},{"id":14604,"chapter_id":39,"file_size":20631680.0,"format":"mp3","audio_url":"https://download.quranicaudio.com/quran/abdullaah_alee_jaabir_studio//039.mp3"},{"id":14605,"chapter_id":40,"file_size":22444160.0,"format":"mp3","audio_url":"https://download.quranicaudio.com/quran/abdullaah_alee_jaabir_studio//040.mp3"},{"id":14606,"chapter_id":41,"file_size":14491776.0,"format":"mp3","audio_url":"https://download.quranicaudio.com/quran/abdullaah_alee_jaabir_studio//041.mp3"},{"id":14607,"chapter_id":42,"file_size":13338752.0,"format":"mp3","audio_url":"https://download.quranicaudio.com/quran/abdullaah_alee_jaabir_studio//042.mp3"},{"id":14608,"chapter_id":43,"file_size":15659136.0,"format":"mp3","audio_url":"https://download.quranicaudio.com/quran/abdullaah_alee_jaabir_studio//043.mp3"},{"id":14609,"chapter_id":44,"file_size":6453376.0,"format":"mp3","audio_url":"https://download.quranicaudio.com/quran/abdullaah_alee_jaabir_studio//044.mp3"},{"id":14610,"chapter_id":45,"file_size":8509568.0,"format":"mp3","audio_url":"https://download.quranicaudio.com/quran/abdullaah_alee_jaabir_studio//045.mp3"},{"id":14611,"chapter_id":46,"file_size":9257088.0,"format":"mp3","audio_url":"https://download.quranicaudio.com/quran/abdullaah_alee_jaabir_studio//046.mp3"},{"id":14612,"chapter_id":47,"file_size":10619008.0,"format":"mp3","audio_url":"https://download.quranicaudio.com/quran/abdullaah_alee_jaabir_studio//047.mp3"},{"id":14613,"chapter_id":48,"file_size":8110208.0,"format":"mp3","audio_url":"https://download.quranicaudio.com/quran/abdullaah_alee_jaabir_studio//048.mp3"},{"id":14614,"chapter_id":49,"file_size":6078592.0,"format":"mp3","audio_url":"https://download.quranicaudio.com/quran/abdullaah_alee_jaabir_studio//049.mp3"},{"id":14615,"chapter_id":50,"file_size":7630976.0,"format":"mp3","audio_url":"https://download.quranicaudio.com/quran/abdullaah_alee_jaabir_studio//050.mp3"},{"id":14616,"chapter_id":51,"file_size":5906560.0,"format":"mp3","audio_url":"https://download.quranicaudio.com/quran/abdullaah_alee_jaabir_studio//051.mp3"},{"id":14617,"chapter_id":52,"file_size":6721664.0,"format":"mp3","audio_url":"https://download.quranicaudio.com/quran/abdullaah_alee_jaabir_studio//052.mp3"},{"id":14618,"chapter_id":53,"file_size":4939904.0,"format":"mp3","audio_url":"https://download.quranicaudio.com/quran/abdullaah_alee_jaabir_studio//053.mp3"},{"id":14619,"chapter_id":54,"file_size":6178944.0,"format":"mp3","audio_url":"https://download.quranicaudio.com/quran/abdullaah_alee_jaabir_studio//054.mp3"},{"id":14620,"chapter_id":55,"file_size":8536192.0,"format":"mp3","audio_url":"https://download.quranicaudio.com/quran/abdullaah_alee_jaabir_studio//055.mp3"},{"id":14621,"chapter_id":56,"file_size":7628928.0,"format":"mp3","audio_url":"https://download.quranicaudio.com/quran/abdullaah_alee_jaabir_studio//056.mp3"},{"id":14622,"chapter_id":57,"file_size":8773760.0,"format":"mp3","audio_url":"https://download.quranicaudio.com/quran/abdullaah_alee_jaabir_studio//057.mp3"},{"id":14623,"chapter_id":58,"file_size":8525952.0,"format":"mp3","audio_url":"https://download.quranicaudio.com/quran/abdullaah_alee_jaabir_studio//058.mp3"},{"id":14624,"chapter_id":59,"file_size":9265280.0,"format":"mp3","audio_url":"https://download.quranicaudio.com/quran/abdullaah_alee_jaabir_studio//059.mp3"},{"id":14625,"chapter_id":60,"file_size":6322304.0,"format":"mp3","audio_url":"https://download.quranicaudio.com/quran/abdullaah_alee_jaabir_studio//060.mp3"},{"id":14626,"chapter_id":61,"file_size":4835456.0,"format":"mp3","audio_url":"https://download.quranicaudio.com/quran/abdullaah_alee_jaabir_studio//061.mp3"},{"id":14627,"chapter_id":62,"file_size":3248256.0,"format":"mp3","audio_url":"https://download.quranicaudio.com/quran/abdullaah_alee_jaabir_studio//062.mp3"},{"id":14628,"chapter_id":63,"file_size":4044928.0,"format":"mp3","audio_url":"https://download.quranicaudio.com/quran/abdullaah_alee_jaabir_studio//063.mp3"},{"id":14629,"chapter_id":64,"file_size":3696768.0,"format":"mp3","audio_url":"https://download.quranicaudio.com/quran/abdullaah_alee_jaabir_studio//064.mp3"},{"id":14630,"chapter_id":65,"file_size":4364416.0,"format":"mp3","audio_url":"https://download.quranicaudio.com/quran/abdullaah_alee_jaabir_studio//065.mp3"},{"id":14631,"chapter_id":66,"file_size":5943424.0,"format":"mp3","audio_url":"https://download.quranicaudio.com/quran/abdullaah_alee_jaabir_studio//066.mp3"},{"id":14632,"chapter_id":67,"file_size":5476480.0,"format":"mp3","audio_url":"https://download.quranicaudio.com/quran/abdullaah_alee_jaabir_studio//067.mp3"},{"id":14633,"chapter_id":68,"file_size":6193280.0,"format":"mp3","audio_url":"https://download.quranicaudio.com/quran/abdullaah_alee_jaabir_studio//068.mp3"},{"id":14634,"chapter_id":69,"file_size":6529152.0,"format":"mp3","audio_url":"https://download.quranicaudio.com/quran/abdullaah_alee_jaabir_studio//069.mp3"},{"id":14635,"chapter_id":70,"file_size":3954816.0,"format":"mp3","audio_url":"https://download.quranicaudio.com/quran/abdullaah_alee_jaabir_studio//070.mp3"},{"id":14636,"chapter_id":71,"file_size":4106368.0,"format":"mp3","audio_url":"https://download.quranicaudio.com/quran/abdullaah_alee_jaabir_studio//071.mp3"},{"id":14637,"chapter_id":72,"file_size":3747968.0,"format":"mp3","audio_url":"https://download.quranicaudio.com/quran/abdullaah_alee_jaabir_studio//072.mp3"},{"id":14638,"chapter_id":73,"file_size":3479680.0,"format":"mp3","audio_url":"https://download.quranicaudio.com/quran/abdullaah_alee_jaabir_studio//073.mp3"},{"id":14639,"chapter_id":74,"file_size":4550784.0,"format":"mp3","audio_url":"https://download.quranicaudio.com/quran/abdullaah_alee_jaabir_studio//074.mp3"},{"id":14640,"chapter_id":75,"file_size":3342464.0,"format":"mp3","audio_url":"https://download.quranicaudio.com/quran/abdullaah_alee_jaabir_studio//075.mp3"},{"id":14641,"chapter_id":76,"file_size":4694144.0,"format":"mp3","audio_url":"https://download.quranicaudio.com/quran/abdullaah_alee_jaabir_studio//076.mp3"},{"id":14642,"chapter_id":77,"file_size":3704960.0,"format":"mp3","audio_url":"https://download.quranicaudio.com/quran/abdullaah_alee_jaabir_studio//077.mp3"},{"id":14643,"chapter_id":78,"file_size":3049600.0,"format":"mp3","audio_url":"https://download.quranicaudio.com/quran/abdullaah_alee_jaabir_studio//078.mp3"},{"id":14644,"chapter_id":79,"file_size":2881664.0,"format":"mp3","audio_url":"https://download.quranicaudio.com/quran/abdullaah_alee_jaabir_studio//079.mp3"},{"id":14645,"chapter_id":80,"file_size":2209920.0,"format":"mp3","audio_url":"https://download.quranicaudio.com/quran/abdullaah_alee_jaabir_studio//080.mp3"},{"id":14646,"chapter_id":81,"file_size":1544320.0,"format":"mp3","audio_url":"https://download.quranicaudio.com/quran/abdullaah_alee_jaabir_studio//081.mp3"},{"id":14647,"chapter_id":82,"file_size":1243264.0,"format":"mp3","audio_url":"https://download.quranicaudio.com/quran/abdullaah_alee_jaabir_studio//082.mp3"},{"id":14648,"chapter_id":83,"file_size":2891904.0,"format":"mp3","audio_url":"https://download.quranicaudio.com/quran/abdullaah_alee_jaabir_studio//083.mp3"},{"id":14649,"chapter_id":84,"file_size":1900672.0,"format":"mp3","audio_url":"https://download.quranicaudio.com/quran/abdullaah_alee_jaabir_studio//084.mp3"},{"id":14650,"chapter_id":85,"file_size":2117760.0,"format":"mp3","audio_url":"https://download.quranicaudio.com/quran/abdullaah_alee_jaabir_studio//085.mp3"},{"id":14651,"chapter_id":86,"file_size":915584.0,"format":"mp3","audio_url":"https://download.quranicaudio.com/quran/abdullaah_alee_jaabir_studio//086.mp3"},{"id":14652,"chapter_id":87,"file_size":931968.0,"format":"mp3","audio_url":"https://download.quranicaudio.com/quran/abdullaah_alee_jaabir_studio//087.mp3"},{"id":14653,"chapter_id":88,"file_size":1773696.0,"format":"mp3","audio_url":"https://download.quranicaudio.com/quran/abdullaah_alee_jaabir_studio//088.mp3"},{"id":14654,"chapter_id":89,"file_size":2535552.0,"format":"mp3","audio_url":"https://download.quranicaudio.com/quran/abdullaah_alee_jaabir_studio//089.mp3"},{"id":14655,"chapter_id":90,"file_size":1063040.0,"format":"mp3","audio_url":"https://download.quranicaudio.com/quran/abdullaah_alee_jaabir_studio//090.mp3"},{"id":14656,"chapter_id":91,"file_size":786560.0,"format":"mp3","audio_url":"https://download.quranicaudio.com/quran/abdullaah_alee_jaabir_studio//091.mp3"},{"id":14657,"chapter_id":92,"file_size":1316992.0,"format":"mp3","audio_url":"https://download.quranicaudio.com/quran/abdullaah_alee_jaabir_studio//092.mp3"},{"id":14658,"chapter_id":93,"file_size":622720.0,"format":"mp3","audio_url":"https://download.quranicaudio.com/quran/abdullaah_alee_jaabir_studio//093.mp3"},{"id":14659,"chapter_id":94,"file_size":370816.0,"format":"mp3","audio_url":"https://download.quranicaudio.com/quran/abdullaah_alee_jaabir_studio//094.mp3"},{"id":14660,"chapter_id":95,"file_size":540800.0,"format":"mp3","audio_url":"https://download.quranicaudio.com/quran/abdullaah_alee_jaabir_studio//095.mp3"},{"id":14661,"chapter_id":96,"file_size":1147008.0,"format":"mp3","audio_url":"https://download.quranicaudio.com/quran/abdullaah_alee_jaabir_studio//096.mp3"},{"id":14662,"chapter_id":97,"file_size":436352.0,"format":"mp3","audio_url":"https://download.quranicaudio.com/quran/abdullaah_alee_jaabir_studio//097.mp3"},{"id":14663,"chapter_id":98,"file_size":1298560.0,"format":"mp3","audio_url":"https://download.quranicaudio.com/quran/abdullaah_alee_jaabir_studio//098.mp3"},{"id":14664,"chapter_id":99,"file_size":540800.0,"format":"mp3","audio_url":"https://download.quranicaudio.com/quran/abdullaah_alee_jaabir_studio//099.mp3"},{"id":14665,"chapter_id":100,"file_size":749696.0,"format":"mp3","audio_url":"https://download.quranicaudio.com/quran/abdullaah_alee_jaabir_studio//100.mp3"},{"id":14666,"chapter_id":101,"file_size":546944.0,"format":"mp3","audio_url":"https://download.quranicaudio.com/quran/abdullaah_alee_jaabir_studio//101.mp3"},{"id":14667,"chapter_id":102,"file_size":651392.0,"format":"mp3","audio_url":"https://download.quranicaudio.com/quran/abdullaah_alee_jaabir_studio//102.mp3"},{"id":14668,"chapter_id":103,"file_size":260224.0,"format":"mp3","audio_url":"https://download.quranicaudio.com/quran/abdullaah_alee_jaabir_studio//103.mp3"},{"id":14669,"chapter_id":104,"file_size":483456.0,"format":"mp3","audio_url":"https://download.quranicaudio.com/quran/abdullaah_alee_jaabir_studio//104.mp3"},{"id":14670,"chapter_id":105,"file_size":387200.0,"format":"mp3","audio_url":"https://download.quranicaudio.com/quran/abdullaah_alee_jaabir_studio//105.mp3"},{"id":14671,"chapter_id":106,"file_size":321664.0,"format":"mp3","audio_url":"https://download.quranicaudio.com/quran/abdullaah_alee_jaabir_studio//106.mp3"},{"id":14672,"chapter_id":107,"file_size":491648.0,"format":"mp3","audio_url":"https://download.quranicaudio.com/quran/abdullaah_alee_jaabir_studio//107.mp3"},{"id":14673,"chapter_id":108,"file_size":174208.0,"format":"mp3","audio_url":"https://download.quranicaudio.com/quran/abdullaah_alee_jaabir_studio//108.mp3"},{"id":14674,"chapter_id":109,"file_size":352384.0,"format":"mp3","audio_url":"https://download.quranicaudio.com/quran/abdullaah_alee_jaabir_studio//109.mp3"},{"id":14675,"chapter_id":110,"file_size":336000.0,"format":"mp3","audio_url":"https://download.quranicaudio.com/quran/abdullaah_alee_jaabir_studio//110.mp3"},{"id":14676,"chapter_id":111,"file_size":360576.0,"format":"mp3","audio_url":"https://download.quranicaudio.com/quran/abdullaah_alee_jaabir_studio//111.mp3"},{"id":14677,"chapter_id":112,"file_size":1423488.0,"format":"mp3","audio_url":"https://download.quranicaudio.com/quran/abdullaah_alee_jaabir_studio//112.mp3"},{"id":14678,"chapter_id":113,"file_size":1921152.0,"format":"mp3","audio_url":"https://download.quranicaudio.com/quran/abdullaah_alee_jaabir_studio//113.mp3"},{"id":14679,"chapter_id":114,"file_size":2361472.0,"format":"mp3","audio_url":"https://download.quranicaudio.com/quran/abdullaah_alee_jaabir_studio//114.mp3"}]}
